[
    {
        "type": "kv",
        "content": [
            {
                "Details": ""
            },
            {
                "12:25PM": ""
            },
            {
                "Employee": ""
            },
            {
                "Roster": ""
            },
            {
                "with": ""
            }
        ]
    },
    {
        "type": "table",
        "content": [
            {
                "Name": "Adair, Christopher M.",
                "I.D.": "022070",
                "Sex": "M",
                "Birth Date": "1978",
                "Age": "41",
                "Employee Type": "Peace Officer",
                "Employee": "\uf0fc",
                "Instructor": "null",
                "Supervisor": "null"
            },
            {
                "Name": "Adame, Jesse A.",
                "I.D.": "025042",
                "Sex": "M",
                "Birth Date": "1988",
                "Age": "31",
                "Employee Type": "Peace Officer",
                "Employee": "\uf0fc",
                "Instructor": "null",
                "Supervisor": "null"
            },
            {
                "Name": "Adams, Ashley A.",
                "I.D.": "025657",
                "Sex": "F",
                "Birth Date": "-1990",
                "Age": "28",
                "Employee Type": "Detention & Correction",
                "Employee": "\uf0fc",
                "Instructor": "null",
                "Supervisor": "null"
            },
            {
                "Name": "Adams, Jeremiah A.",
                "I.D.": "020885",
                "Sex": "M",
                "Birth Date": "1984",
                "Age": "35",
                "Employee Type": "Peace Officer",
                "Employee": "\uf0fc",
                "Instructor": "null",
                "Supervisor": "null"
            },
            {
                "Name": "Adams, Ross E.",
                "I.D.": "000012",
                "Sex": "M",
                "Birth Date": "1960",
                "Age": "59",
                "Employee Type": "Peace Officer",
                "Employee": "\uf0fc",
                "Instructor": "null",
                "Supervisor": "null"
            },
            {
                "Name": "Adams, Seth H.",
                "I.D.": "022864",
                "Sex": "M",
                "Birth Date": "1989",
                "Age": "30",
                "Employee Type": "Peace Officer",
                "Employee": "\uf0fc",
                "Instructor": "null",
                "Supervisor": "null"
            },
            {
                "Name": "Adams, Tyler",
                "I.D.": "023612",
                "Sex": "M",
                "Birth Date": "-1984",
                "Age": "34",
                "Employee Type": "Detention & Correction",
                "Employee": "\uf0fc",
                "Instructor": "null",
                "Supervisor": "null"
            },
            {
                "Name": "Adkins, Kevin",
                "I.D.": "016759",
                "Sex": "null",
                "Birth Date": "null",
                "Age": "null",
                "Employee Type": "Peace Officer",
                "Employee": "\uf0fc",
                "Instructor": "null",
                "Supervisor": "null"
            },
            {
                "Name": "Adolph, Jerry O.",
                "I.D.": "014668",
                "Sex": "M",
                "Birth Date": "-1959",
                "Age": "59",
                "Employee Type": "Detention & Correction",
                "Employee": "\uf0fc",
                "Instructor": "null",
                "Supervisor": "null"
            },
            {
                "Name": "Adorni, Larry F.",
                "I.D.": "016753",
                "Sex": "M",
                "Birth Date": "1957",
                "Age": "62",
                "Employee Type": "Peace Officer",
                "Employee": "\uf0fc",
                "Instructor": "null",
                "Supervisor": "null"
            },
            {
                "Name": "Adsem, Steven J.",
                "I.D.": "005552",
                "Sex": "M",
                "Birth Date": "1965",
                "Age": "54",
                "Employee Type": "Peace Officer",
                "Employee": "\uf0fc",
                "Instructor": "null",
                "Supervisor": "null"
            },
            {
                "Name": "Aggers, Mary",
                "I.D.": "012393",
                "Sex": "F",
                "Birth Date": "1970",
                "Age": "49",
                "Employee Type": "Probation & Parole",
                "Employee": "\uf0fc",
                "Instructor": "null",
                "Supervisor": "null"
            },
            {
                "Name": "Ahlin, Benjamin J.",
                "I.D.": "024854",
                "Sex": "M",
                "Birth Date": "1993",
                "Age": "26",
                "Employee Type": "Detention & Correction",
                "Employee": "\uf0fc",
                "Instructor": "null",
                "Supervisor": "null"
            },
            {
                "Name": "Ahmann, Jacob G.",
                "I.D.": "023943",
                "Sex": "M",
                "Birth Date": "1992",
                "Age": "27",
                "Employee Type": "Peace Officer",
                "Employee": "\uf0fc",
                "Instructor": "null",
                "Supervisor": "null"
            },
            {
                "Name": "Aiello, Antonio D.",
                "I.D.": "023659",
                "Sex": "M",
                "Birth Date": "1984",
                "Age": "35",
                "Employee Type": "Detention & Correction",
                "Employee": "\uf0fc",
                "Instructor": "null",
                "Supervisor": "null"
            },
            {
                "Name": "Albright, Christopher B.",
                "I.D.": "010496",
                "Sex": "M",
                "Birth Date": "1970",
                "Age": "49",
                "Employee Type": "Peace Officer",
                "Employee": "\uf0fc",
                "Instructor": "null",
                "Supervisor": "null"
            },
            {
                "Name": "Albright, Cody J.",
                "I.D.": "021589",
                "Sex": "M",
                "Birth Date": "1990",
                "Age": "29",
                "Employee Type": "Detention & Correction",
                "Employee": "\uf0fc",
                "Instructor": "null",
                "Supervisor": "null"
            },
            {
                "Name": "Aliperto, Benjamin J.",
                "I.D.": "025733",
                "Sex": "M",
                "Birth Date": "1995",
                "Age": "24",
                "Employee Type": "Detention & Correction",
                "Employee": "\uf0fc",
                "Instructor": "null",
                "Supervisor": "null"
            },
            {
                "Name": "Allen, Darin C.",
                "I.D.": "015463",
                "Sex": "M",
                "Birth Date": "1974",
                "Age": "45",
                "Employee Type": "Probation & Parole",
                "Employee": "\uf0fc",
                "Instructor": "null",
                "Supervisor": "null"
            },
            {
                "Name": "Allen, Jack E.",
                "I.D.": "000025",
                "Sex": "M",
                "Birth Date": "-1959",
                "Age": "59",
                "Employee Type": "Peace Officer",
                "Employee": "\uf0fc",
                "Instructor": "null",
                "Supervisor": "null"
            },
            {
                "Name": "Allen, Jesse C.",
                "I.D.": "021937",
                "Sex": "M",
                "Birth Date": "1982",
                "Age": "37",
                "Employee Type": "Peace Officer",
                "Employee": "\uf0fc",
                "Instructor": "null",
                "Supervisor": "null"
            },
            {
                "Name": "Allen, Payton E.",
                "I.D.": "025919",
                "Sex": "M",
                "Birth Date": "1999",
                "Age": "20",
                "Employee Type": "Detention & Correction",
                "Employee": "\uf0fc",
                "Instructor": "null",
                "Supervisor": "null"
            },
            {
                "Name": "Allen, Robert J.",
                "I.D.": "025593",
                "Sex": "M",
                "Birth Date": "1976",
                "Age": "43",
                "Employee Type": "Peace Officer",
                "Employee": "\uf0fc",
                "Instructor": "null",
                "Supervisor": "null"
            },
            {
                "Name": "Allen, Sean C.",
                "I.D.": "024063",
                "Sex": "M",
                "Birth Date": "-1986",
                "Age": "32",
                "Employee Type": "Peace Officer",
                "Employee": "\uf0fc",
                "Instructor": "null",
                "Supervisor": "null"
            },
            {
                "Name": "Allen, Tammy A.",
                "I.D.": "017266",
                "Sex": "null",
                "Birth Date": "-1967",
                "Age": "51",
                "Employee Type": "Detention & Correction",
                "Employee": "\uf0fc",
                "Instructor": "null",
                "Supervisor": "null"
            },
            {
                "Name": "Allison, Derek",
                "I.D.": "025076",
                "Sex": "M",
                "Birth Date": "1999",
                "Age": "20",
                "Employee Type": "Detention & Correction",
                "Employee": "\uf0fc",
                "Instructor": "null",
                "Supervisor": "null"
            },
            {
                "Name": "Allison, Thomas B.",
                "I.D.": "022103",
                "Sex": "M",
                "Birth Date": "-1992",
                "Age": "26",
                "Employee Type": "Peace Officer",
                "Employee": "\uf0fc",
                "Instructor": "null",
                "Supervisor": "null"
            },
            {
                "Name": "Allmendinger, Jacob O.",
                "I.D.": "020851",
                "Sex": "M",
                "Birth Date": "-1987",
                "Age": "31",
                "Employee Type": "Peace Officer",
                "Employee": "\uf0fc",
                "Instructor": "null",
                "Supervisor": "null"
            },
            {
                "Name": "Allred, Sabrina",
                "I.D.": "025094",
                "Sex": "F",
                "Birth Date": "1978",
                "Age": "41",
                "Employee Type": "Probation & Parole",
                "Employee": "\uf0fc",
                "Instructor": "null",
                "Supervisor": "null"
            },
            {
                "Name": "Althaus, Terry L.",
                "I.D.": "000028",
                "Sex": "M",
                "Birth Date": "1960",
                "Age": "59",
                "Employee Type": "Peace Officer",
                "Employee": "\uf0fc",
                "Instructor": "null",
                "Supervisor": "null"
            },
            {
                "Name": "Altmiller, Jason D.",
                "I.D.": "024024",
                "Sex": "null",
                "Birth Date": "null",
                "Age": "null",
                "Employee Type": "Peace Officer",
                "Employee": "\uf0fc",
                "Instructor": "null",
                "Supervisor": "null"
            },
            {
                "Name": "Altschwager, Daniel T.",
                "I.D.": "020936",
                "Sex": "M",
                "Birth Date": "-1983",
                "Age": "35",
                "Employee Type": "Peace Officer",
                "Employee": "\uf0fc",
                "Instructor": "null",
                "Supervisor": "null"
            }
        ]
    }
]