{
    "node0": {
        "type": "kv",
        "child": 5,
        "fields": [
            "Date",
            "Status",
            "Action"
        ],
        "bid": [
            14
        ]
    },
    "node1": {
        "type": "table",
        "fields": [
            "Date",
            "Status",
            "Certified",
            "Expires",
            "Probation",
            "Cert #"
        ],
        "bid": [
            1
        ],
        "child": -1
    },
    "node2": {
        "type": "kv",
        "fields": [
            "Assignment",
            "VT State Police",
            "Years",
            "Pos/Rank",
            "Action",
            "Days",
            "Date",
            "Status",
            "Full-time",
            "Service"
        ],
        "bid": [
            2
        ],
        "child": -1
    },
    "node3": {
        "type": "table",
        "fields": [
            "Level",
            "Class",
            "Level III"
        ],
        "bid": [
            3
        ],
        "child": 4
    },
    "node4": {
        "type": "kv",
        "fields": [
            "Assignment",
            "Shift",
            "Pos/Rank",
            "Action",
            "Class",
            "Date",
            "Level",
            "Status"
        ],
        "bid": [
            5
        ],
        "child": -1
    },
    "node5": {
        "type": "table",
        "fields": [
            "Level",
            "Class"
        ],
        "bid": [
            7
        ],
        "child": -1
    }
}